{"template":{"small":"https://static-cdn.jtvnw.net/emoticons/v1/{image_id}/1.0","medium":"https://static-cdn.jtvnw.net/emoticons/v1/{image_id}/2.0","large":"https://static-cdn.jtvnw.net/emoticons/v1/{image_id}/3.0"},"channels":{"avidyazen":{"title":"AvidyaZEN","channel_id":24874112,"link":"http://twitch.tv/avidyazen","desc":null,"plans":{"$4.99":"8298","$9.99":"30317","$24.99":"30318"},"id":"avidyazen","first_seen":null,"badge":"https://static-cdn.jtvnw.net/badges/v1/961f68a0-2cd1-4529-8c31-ee19720bef3a/1","badge_starting":"https://static-cdn.jtvnw.net/badges/v1/961f68a0-2cd1-4529-8c31-ee19720bef3a/3","badge_3m":null,"badge_6m":null,"badge_12m":null,"badge_24m":null,"badges":[{"image_url_1x":"https://static-cdn.jtvnw.net/badges/v1/961f68a0-2cd1-4529-8c31-ee19720bef3a/1","image_url_2x":"https://static-cdn.jtvnw.net/badges/v1/961f68a0-2cd1-4529-8c31-ee19720bef3a/2","image_url_4x":"https://static-cdn.jtvnw.net/badges/v1/961f68a0-2cd1-4529-8c31-ee19720bef3a/3","description":"Subscriber","title":"Subscriber","click_action":"subscribe_to_channel","click_url":""}],"bits_badges":null,"cheermote1":null,"cheermote100":null,"cheermote1000":null,"cheermote5000":null,"cheermote10000":null,"set":8298,"emotes":[{"code":"zenYeah","image_id":48530,"set":8298},{"code":"zenGold","image_id":175861,"set":30318},{"code":"zenDude","image_id":162365,"set":8298},{"code":"zenShades","image_id":162364,"set":8298},{"code":"zenHype","image_id":165737,"set":8298},{"code":"zenPalm","image_id":162253,"set":8298},{"code":"zenPurp","image_id":175860,"set":30317},{"code":"zenChill","image_id":178455,"set":8298}]}}}
