{"template":{"small":"https://static-cdn.jtvnw.net/emoticons/v1/{image_id}/1.0","medium":"https://static-cdn.jtvnw.net/emoticons/v1/{image_id}/2.0","large":"https://static-cdn.jtvnw.net/emoticons/v1/{image_id}/3.0"},"channels":{"bananas":{"title":"Bananas","channel_id":"31149715","link":"http://twitch.tv/bananas","desc":null,"id":"bananas","first_seen":null,"badge":"https://static-cdn.jtvnw.net/jtv_user_pictures/badges/2160/18x18.png","badge_starting":null,"badge_3m":null,"badge_6m":null,"badge_12m":null,"badge_24m":null,"set":4493,"emotes":[{"code":"bananCorg","image_id":14564},{"code":"bananFrosty","image_id":13788},{"code":"bananLuka","image_id":14644},{"code":"bananMiku","image_id":16862},{"code":"bananGumi","image_id":16868},{"code":"bananRin","image_id":16863}]}}}
