{"template":{"small":"https://static-cdn.jtvnw.net/emoticons/v1/{image_id}/1.0","medium":"https://static-cdn.jtvnw.net/emoticons/v1/{image_id}/2.0","large":"https://static-cdn.jtvnw.net/emoticons/v1/{image_id}/3.0"},"channels":{"belynz":{"title":"Belynz","link":"http://twitch.tv/belynz","desc":null,"id":"belynz","first_seen":null,"badge":"https://static-cdn.jtvnw.net/jtv_user_pictures/badges/1306/18x18.png","set":1849,"emotes":[{"code":"bellEND","image_id":6189},{"code":"bellTato","image_id":9413},{"code":"bellREC","image_id":39887},{"code":"bellJUDGE","image_id":91632},{"code":"bellWUT","image_id":74767},{"code":"bellKapppa","image_id":60135},{"code":"bellSLAY","image_id":75157},{"code":"bellSWEG","image_id":76365},{"code":"bellLEMON","image_id":104727},{"code":"bellIFFF","image_id":104724}]}}}
