{"template":{"small":"https://static-cdn.jtvnw.net/emoticons/v1/{image_id}/1.0","medium":"https://static-cdn.jtvnw.net/emoticons/v1/{image_id}/2.0","large":"https://static-cdn.jtvnw.net/emoticons/v1/{image_id}/3.0"},"channels":{"blaskatronic":{"title":"Blaskatronic","channel_id":30004616,"link":"http://twitch.tv/blaskatronic","desc":null,"plans":{"$4.99":"126722","$9.99":"126725","$24.99":"126726"},"id":"blaskatronic","first_seen":"2017-07-05 06:15:04","badge":null,"badge_starting":null,"badge_3m":null,"badge_6m":null,"badge_12m":null,"badge_24m":null,"badges":null,"bits_badges":null,"cheermote1":null,"cheermote100":null,"cheermote1000":null,"cheermote5000":null,"cheermote10000":null,"set":126725,"emotes":[{"code":"blaskaDoryx","image_id":225278,"set":126725},{"code":"blaskaWitz","image_id":225229,"set":126722}]}}}
