{"template":{"small":"https://static-cdn.jtvnw.net/emoticons/v1/{image_id}/1.0","medium":"https://static-cdn.jtvnw.net/emoticons/v1/{image_id}/2.0","large":"https://static-cdn.jtvnw.net/emoticons/v1/{image_id}/3.0"},"channels":{"bosteed":{"title":"BoSteed","channel_id":42429615,"link":"http://twitch.tv/bosteed","desc":null,"plans":{"$4.99":"139789","$9.99":"139790","$24.99":"139791"},"id":"bosteed","first_seen":"2017-07-05 06:15:05","badge":null,"badge_starting":null,"badge_3m":null,"badge_6m":null,"badge_12m":null,"badge_24m":null,"badges":null,"bits_badges":null,"cheermote1":null,"cheermote100":null,"cheermote1000":null,"cheermote5000":null,"cheermote10000":null,"set":139789,"emotes":[{"code":"bosteeFail","image_id":260122,"set":139789},{"code":"bosteeDatbo","image_id":260126,"set":139790},{"code":"bosteeBoHiYo","image_id":265231,"set":139791}]}}}
