{"template":{"small":"https://static-cdn.jtvnw.net/emoticons/v1/{image_id}/1.0","medium":"https://static-cdn.jtvnw.net/emoticons/v1/{image_id}/2.0","large":"https://static-cdn.jtvnw.net/emoticons/v1/{image_id}/3.0"},"channels":{"breakycpk":{"title":"breakycpk","channel_id":"12832944","link":"http://twitch.tv/breakycpk","desc":null,"id":"breakycpk","first_seen":null,"badge":"https://static-cdn.jtvnw.net/jtv_user_pictures/badges/854/18x18.png","badge_starting":null,"badge_3m":null,"badge_6m":null,"badge_12m":null,"badge_24m":null,"set":403,"emotes":[{"code":"cpkFiesta","image_id":2976},{"code":"cpkKadoosh","image_id":2573},{"code":"cpkSwag","image_id":2766},{"code":"cpkSub","image_id":3314},{"code":"cpkMurica","image_id":3347},{"code":"cpkBacon","image_id":3385},{"code":"cpkPlinko","image_id":3386}]}}}
