{"template":{"small":"https://static-cdn.jtvnw.net/emoticons/v1/{image_id}/1.0","medium":"https://static-cdn.jtvnw.net/emoticons/v1/{image_id}/2.0","large":"https://static-cdn.jtvnw.net/emoticons/v1/{image_id}/3.0"},"channels":{"cacaotv":{"title":"Cacaotv","link":"http://twitch.tv/cacaotv","desc":null,"id":"cacaotv","first_seen":null,"badge":"https://static-cdn.jtvnw.net/jtv_user_pictures/badges/5653/18x18.png","set":11408,"emotes":[{"code":"kkoGreedy","image_id":39640},{"code":"kkoFail","image_id":38998},{"code":"kkoChoco","image_id":39107},{"code":"kkoGg","image_id":40580},{"code":"kkoSuper","image_id":73874}]}}}
