{"template":{"small":"https://static-cdn.jtvnw.net/emoticons/v1/{image_id}/1.0","medium":"https://static-cdn.jtvnw.net/emoticons/v1/{image_id}/2.0","large":"https://static-cdn.jtvnw.net/emoticons/v1/{image_id}/3.0"},"channels":{"cartmanzbs":{"title":"CarTmaNzbs","channel_id":50958896,"link":"http://twitch.tv/cartmanzbs","desc":null,"plans":{"$4.99":"6425","$9.99":"44344","$24.99":"44345"},"id":"cartmanzbs","first_seen":"2016-08-18 13:20:07","badge":"https://static-cdn.jtvnw.net/badges/v1/ef9f26d6-cb67-413c-a822-270f17c9eba3/1","badge_starting":"https://static-cdn.jtvnw.net/badges/v1/ef9f26d6-cb67-413c-a822-270f17c9eba3/3","badge_3m":"https://static-cdn.jtvnw.net/badges/v1/c7f87972-64ff-4ce4-9aad-b83474e41a1e/3","badge_6m":"https://static-cdn.jtvnw.net/badges/v1/8b2164dc-3ec7-455a-97b9-8cdaa8ab110d/3","badge_12m":"https://static-cdn.jtvnw.net/badges/v1/1e213ca2-5e70-4e22-adfc-09b705000069/3","badge_24m":null,"badges":{"0":{"image_url_1x":"https://static-cdn.jtvnw.net/badges/v1/ef9f26d6-cb67-413c-a822-270f17c9eba3/1","image_url_2x":"https://static-cdn.jtvnw.net/badges/v1/ef9f26d6-cb67-413c-a822-270f17c9eba3/2","image_url_4x":"https://static-cdn.jtvnw.net/badges/v1/ef9f26d6-cb67-413c-a822-270f17c9eba3/3","description":"Subscriber","title":"Subscriber","click_action":"subscribe_to_channel","click_url":""},"3":{"image_url_1x":"https://static-cdn.jtvnw.net/badges/v1/c7f87972-64ff-4ce4-9aad-b83474e41a1e/1","image_url_2x":"https://static-cdn.jtvnw.net/badges/v1/c7f87972-64ff-4ce4-9aad-b83474e41a1e/2","image_url_4x":"https://static-cdn.jtvnw.net/badges/v1/c7f87972-64ff-4ce4-9aad-b83474e41a1e/3","description":"3-Month Subscriber","title":"3-Month Subscriber","click_action":"subscribe_to_channel","click_url":""},"6":{"image_url_1x":"https://static-cdn.jtvnw.net/badges/v1/8b2164dc-3ec7-455a-97b9-8cdaa8ab110d/1","image_url_2x":"https://static-cdn.jtvnw.net/badges/v1/8b2164dc-3ec7-455a-97b9-8cdaa8ab110d/2","image_url_4x":"https://static-cdn.jtvnw.net/badges/v1/8b2164dc-3ec7-455a-97b9-8cdaa8ab110d/3","description":"6-Month Subscriber","title":"6-Month Subscriber","click_action":"subscribe_to_channel","click_url":""},"12":{"image_url_1x":"https://static-cdn.jtvnw.net/badges/v1/1e213ca2-5e70-4e22-adfc-09b705000069/1","image_url_2x":"https://static-cdn.jtvnw.net/badges/v1/1e213ca2-5e70-4e22-adfc-09b705000069/2","image_url_4x":"https://static-cdn.jtvnw.net/badges/v1/1e213ca2-5e70-4e22-adfc-09b705000069/3","description":"1-Year Subscriber","title":"1-Year Subscriber","click_action":"subscribe_to_channel","click_url":""}},"bits_badges":null,"cheermote1":null,"cheermote100":null,"cheermote1000":null,"cheermote5000":null,"cheermote10000":null,"set":6425,"emotes":[{"code":"zbsYshi","image_id":110262,"set":6425},{"code":"zbs8k","image_id":79082,"set":6425},{"code":"zbsBunt","image_id":143732,"set":6425},{"code":"zbsSub","image_id":79948,"set":6425},{"code":"zbs1","image_id":142658,"set":6425},{"code":"zbs2","image_id":142659,"set":6425},{"code":"zbs3","image_id":142661,"set":6425},{"code":"zbs4","image_id":142662,"set":6425},{"code":"zbsArt","image_id":51939,"set":6425},{"code":"zbsAhaha","image_id":143731,"set":6425},{"code":"zbsTobipizda","image_id":143730,"set":6425},{"code":"zbsKeepo","image_id":116735,"set":6425},{"code":"zbsSkip","image_id":116734,"set":6425},{"code":"zbsOh","image_id":118894,"set":6425},{"code":"zbsDemon","image_id":124938,"set":6425},{"code":"zbsMcat","image_id":124940,"set":6425},{"code":"zbsRun","image_id":124971,"set":6425},{"code":"zbsMinys50","image_id":124987,"set":6425},{"code":"zbsBan","image_id":142053,"set":6425},{"code":"zbsBlet","image_id":203309,"set":6425}]}}}
