{"template":{"small":"https://static-cdn.jtvnw.net/emoticons/v1/{image_id}/1.0","medium":"https://static-cdn.jtvnw.net/emoticons/v1/{image_id}/2.0","large":"https://static-cdn.jtvnw.net/emoticons/v1/{image_id}/3.0"},"channels":{"copenhagengamessc2":{"title":"CopenhagenGamesSC2","channel_id":60021718,"link":"http://twitch.tv/copenhagengamessc2","desc":null,"plans":{"$4.99":null,"$9.99":null,"$24.99":null},"id":"copenhagengamessc2","first_seen":null,"badge":null,"badge_starting":null,"badge_3m":null,"badge_6m":null,"badge_12m":null,"badge_24m":null,"badges":null,"bits_badges":null,"cheermote1":null,"cheermote100":null,"cheermote1000":null,"cheermote5000":null,"cheermote10000":null,"set":12560,"emotes":[{"code":"cphBang","image_id":45427,"set":12560},{"code":"cphGames","image_id":45428,"set":12560},{"code":"cphDk","image_id":45429,"set":12560},{"code":"cphSmiley","image_id":45430,"set":12560},{"code":"cphThumbs","image_id":45431,"set":12560}]}}}
