{"template":{"small":"https://static-cdn.jtvnw.net/emoticons/v1/{image_id}/1.0","medium":"https://static-cdn.jtvnw.net/emoticons/v1/{image_id}/2.0","large":"https://static-cdn.jtvnw.net/emoticons/v1/{image_id}/3.0"},"channels":{"cougarob":{"title":"Cougarob","channel_id":88170091,"link":"http://twitch.tv/cougarob","desc":null,"plans":{"$4.99":"16151","$9.99":"23293","$24.99":"23294"},"id":"cougarob","first_seen":null,"badge":"https://static-cdn.jtvnw.net/badges/v1/d44eaf9c-daa6-49af-8315-5d155f242d1b/1","badge_starting":"https://static-cdn.jtvnw.net/badges/v1/d44eaf9c-daa6-49af-8315-5d155f242d1b/3","badge_3m":"https://static-cdn.jtvnw.net/badges/v1/7a161186-1c61-4bfa-ab8b-974c8576a6ed/3","badge_6m":"https://static-cdn.jtvnw.net/badges/v1/be99c1f0-ed3c-429f-a66f-df0a38e0e732/3","badge_12m":"https://static-cdn.jtvnw.net/badges/v1/95548115-a1c7-4110-baba-9566aa9b8d50/3","badge_24m":null,"badges":{"0":{"image_url_1x":"https://static-cdn.jtvnw.net/badges/v1/d44eaf9c-daa6-49af-8315-5d155f242d1b/1","image_url_2x":"https://static-cdn.jtvnw.net/badges/v1/d44eaf9c-daa6-49af-8315-5d155f242d1b/2","image_url_4x":"https://static-cdn.jtvnw.net/badges/v1/d44eaf9c-daa6-49af-8315-5d155f242d1b/3","description":"Subscriber","title":"Subscriber","click_action":"subscribe_to_channel","click_url":""},"3":{"image_url_1x":"https://static-cdn.jtvnw.net/badges/v1/7a161186-1c61-4bfa-ab8b-974c8576a6ed/1","image_url_2x":"https://static-cdn.jtvnw.net/badges/v1/7a161186-1c61-4bfa-ab8b-974c8576a6ed/2","image_url_4x":"https://static-cdn.jtvnw.net/badges/v1/7a161186-1c61-4bfa-ab8b-974c8576a6ed/3","description":"3-Month Subscriber","title":"3-Month Subscriber","click_action":"subscribe_to_channel","click_url":""},"6":{"image_url_1x":"https://static-cdn.jtvnw.net/badges/v1/be99c1f0-ed3c-429f-a66f-df0a38e0e732/1","image_url_2x":"https://static-cdn.jtvnw.net/badges/v1/be99c1f0-ed3c-429f-a66f-df0a38e0e732/2","image_url_4x":"https://static-cdn.jtvnw.net/badges/v1/be99c1f0-ed3c-429f-a66f-df0a38e0e732/3","description":"6-Month Subscriber","title":"6-Month Subscriber","click_action":"subscribe_to_channel","click_url":""},"12":{"image_url_1x":"https://static-cdn.jtvnw.net/badges/v1/95548115-a1c7-4110-baba-9566aa9b8d50/1","image_url_2x":"https://static-cdn.jtvnw.net/badges/v1/95548115-a1c7-4110-baba-9566aa9b8d50/2","image_url_4x":"https://static-cdn.jtvnw.net/badges/v1/95548115-a1c7-4110-baba-9566aa9b8d50/3","description":"1-Year Subscriber","title":"1-Year Subscriber","click_action":"subscribe_to_channel","click_url":""}},"bits_badges":null,"cheermote1":null,"cheermote100":null,"cheermote1000":null,"cheermote5000":null,"cheermote10000":null,"set":16151,"emotes":[{"code":"cougChill","image_id":83927,"set":16151},{"code":"cougDown","image_id":86421,"set":16151},{"code":"cougPack","image_id":84678,"set":16151},{"code":"cougRob","image_id":83277,"set":16151},{"code":"cougCub","image_id":83689,"set":16151},{"code":"cougFlash","image_id":83279,"set":16151},{"code":"cougTrain","image_id":85914,"set":16151},{"code":"cougCrew","image_id":100696,"set":16151},{"code":"cougDeath","image_id":190949,"set":16151},{"code":"cougWham","image_id":201859,"set":16151},{"code":"cougChub","image_id":191584,"set":16151},{"code":"cougWow","image_id":193694,"set":16151},{"code":"cougLurk","image_id":204378,"set":16151},{"code":"cougGold","image_id":187196,"set":23294},{"code":"cougSilver","image_id":187195,"set":23293},{"code":"cougNo","image_id":195977,"set":16151},{"code":"cougDeal","image_id":195978,"set":16151}]}}}
