{"template":{"small":"https://static-cdn.jtvnw.net/emoticons/v1/{image_id}/1.0","medium":"https://static-cdn.jtvnw.net/emoticons/v1/{image_id}/2.0","large":"https://static-cdn.jtvnw.net/emoticons/v1/{image_id}/3.0"},"channels":{"curi0sde":{"title":"curi0sDE","channel_id":"77959115","link":"http://twitch.tv/curi0sde","desc":null,"id":"curi0sde","first_seen":"2016-11-07 12:40:03","badge":"https://static-cdn.jtvnw.net/badges/v1/66ae5142-9612-4091-b607-37d16d0f3437/1","badge_starting":"https://static-cdn.jtvnw.net/badges/v1/66ae5142-9612-4091-b607-37d16d0f3437/3","badge_3m":"https://static-cdn.jtvnw.net/badges/v1/02352125-1634-4ede-96ca-52598584f7ac/3","badge_6m":"https://static-cdn.jtvnw.net/badges/v1/10c9d52c-d8e0-4420-927c-1331ce7b2f42/3","badge_12m":"https://static-cdn.jtvnw.net/badges/v1/2d7df551-fd5b-4d21-8511-a91e0f8a9152/3","badge_24m":"https://static-cdn.jtvnw.net/badges/v1/e7847b72-5df5-47f3-8bbe-32d49e223081/3","set":19717,"emotes":[{"code":"curiBup","image_id":125149},{"code":"curiVM","image_id":125234},{"code":"curiWI","image_id":125843}]}}}
