{"template":{"small":"https://static-cdn.jtvnw.net/emoticons/v1/{image_id}/1.0","medium":"https://static-cdn.jtvnw.net/emoticons/v1/{image_id}/2.0","large":"https://static-cdn.jtvnw.net/emoticons/v1/{image_id}/3.0"},"channels":{"dondlow":{"title":"DonDLow","channel_id":71277796,"link":"http://twitch.tv/dondlow","desc":null,"id":"dondlow","first_seen":"2017-01-20 18:05:12","badge":"https://static-cdn.jtvnw.net/badges/v1/0334e9b0-8fb8-485c-8221-832696e56044/1","badge_starting":"https://static-cdn.jtvnw.net/badges/v1/0334e9b0-8fb8-485c-8221-832696e56044/3","badge_3m":"https://static-cdn.jtvnw.net/badges/v1/f5ea40ce-ff7e-4c4e-97b4-3639d7f02b5f/3","badge_6m":"https://static-cdn.jtvnw.net/badges/v1/4757fac5-7f83-488b-8c94-09019c0bfeeb/3","badge_12m":"https://static-cdn.jtvnw.net/badges/v1/4b2ac0b4-86ee-4772-ac12-c6fb4ba9d7ce/3","badge_24m":"https://static-cdn.jtvnw.net/badges/v1/d57dca63-005c-477d-a426-04fe2ee35696/3","cheermote1":null,"cheermote100":null,"cheermote1000":null,"cheermote5000":null,"cheermote10000":null,"set":16785,"emotes":[{"code":"dondHEY","image_id":142466},{"code":"dondVIP","image_id":129494},{"code":"dondSUB","image_id":89285},{"code":"dondU","image_id":90381},{"code":"dondYOU","image_id":97425},{"code":"dondGG","image_id":126755}]}}}
