{"template":{"small":"https://static-cdn.jtvnw.net/emoticons/v1/{image_id}/1.0","medium":"https://static-cdn.jtvnw.net/emoticons/v1/{image_id}/2.0","large":"https://static-cdn.jtvnw.net/emoticons/v1/{image_id}/3.0"},"channels":{"esl_dexertode":{"title":"ESL_DexertoDE","channel_id":121530962,"link":"http://twitch.tv/esl_dexertode","desc":null,"plans":{"$4.99":"17333","$9.99":"54261","$24.99":"54262"},"id":"esl_dexertode","first_seen":"2016-04-19 21:50:04","badge":"https://static-cdn.jtvnw.net/badges/v1/da77c6b7-d875-40b4-a8a1-6f5b6ebfd520/1","badge_starting":"https://static-cdn.jtvnw.net/badges/v1/da77c6b7-d875-40b4-a8a1-6f5b6ebfd520/3","badge_3m":null,"badge_6m":null,"badge_12m":null,"badge_24m":null,"badges":[{"image_url_1x":"https://static-cdn.jtvnw.net/badges/v1/da77c6b7-d875-40b4-a8a1-6f5b6ebfd520/1","image_url_2x":"https://static-cdn.jtvnw.net/badges/v1/da77c6b7-d875-40b4-a8a1-6f5b6ebfd520/2","image_url_4x":"https://static-cdn.jtvnw.net/badges/v1/da77c6b7-d875-40b4-a8a1-6f5b6ebfd520/3","description":"Subscriber","title":"Subscriber","click_action":"subscribe_to_channel","click_url":""}],"bits_badges":null,"cheermote1":null,"cheermote100":null,"cheermote1000":null,"cheermote5000":null,"cheermote10000":null,"set":17333,"emotes":[{"code":"dexeLeGo","image_id":95592,"set":17333},{"code":"dexeGG","image_id":95591,"set":17333}]}}}
