{"template":{"small":"https://static-cdn.jtvnw.net/emoticons/v1/{image_id}/1.0","medium":"https://static-cdn.jtvnw.net/emoticons/v1/{image_id}/2.0","large":"https://static-cdn.jtvnw.net/emoticons/v1/{image_id}/3.0"},"channels":{"fate_twisted_na":{"title":"Fate_Twisted_NA","channel_id":91137296,"link":"http://twitch.tv/fate_twisted_na","desc":null,"id":"fate_twisted_na","first_seen":"2016-06-26 20:50:03","badge":"https://static-cdn.jtvnw.net/badges/v1/89eb3ab8-51ca-45d4-949a-2381087b8601/1","badge_starting":"https://static-cdn.jtvnw.net/badges/v1/89eb3ab8-51ca-45d4-949a-2381087b8601/3","badge_3m":null,"badge_6m":null,"badge_12m":null,"badge_24m":null,"set":17969,"emotes":[{"code":"ftnaOK","image_id":103983},{"code":"ftnaBROKE","image_id":138484},{"code":"ftnaPRIDE","image_id":130772},{"code":"ftna1","image_id":130849},{"code":"ftna3","image_id":130851},{"code":"ftnaURSELF","image_id":108672},{"code":"ftna4","image_id":130852},{"code":"ftnaGOOD","image_id":108666},{"code":"ftnaWUT","image_id":108664},{"code":"ftna2","image_id":130850},{"code":"ftnaKKANO","image_id":105666},{"code":"ftnaGASM","image_id":103981},{"code":"ftnaKEG","image_id":105665},{"code":"ftnaGUN","image_id":105664},{"code":"ftnaBAD","image_id":105663},{"code":"ftnaWEEB","image_id":105662},{"code":"ftnaRAGE","image_id":108811},{"code":"ftnaSLEEP","image_id":138487},{"code":"ftnaTHUMP","image_id":138488},{"code":"ftnaREE","image_id":138491},{"code":"ftnaORK","image_id":138225},{"code":"ftnaLUL","image_id":138226},{"code":"ftnaCHAMP","image_id":138227},{"code":"ftnaHARD","image_id":138486}]}}}
