{"template":{"small":"https://static-cdn.jtvnw.net/emoticons/v1/{image_id}/1.0","medium":"https://static-cdn.jtvnw.net/emoticons/v1/{image_id}/2.0","large":"https://static-cdn.jtvnw.net/emoticons/v1/{image_id}/3.0"},"channels":{"hawlzz":{"title":"hawlzz","channel_id":62021976,"link":"http://twitch.tv/hawlzz","desc":null,"plans":{"$4.99":"70119","$9.99":"70120","$24.99":"70121"},"id":"hawlzz","first_seen":"2017-07-02 18:25:05","badge":null,"badge_starting":null,"badge_3m":null,"badge_6m":null,"badge_12m":null,"badge_24m":null,"badges":null,"bits_badges":null,"cheermote1":null,"cheermote100":null,"cheermote1000":null,"cheermote5000":null,"cheermote10000":null,"set":70119,"emotes":[{"code":"hawlzzTali","image_id":246946,"set":70119}]}}}
