{"template":{"small":"https://static-cdn.jtvnw.net/emoticons/v1/{image_id}/1.0","medium":"https://static-cdn.jtvnw.net/emoticons/v1/{image_id}/2.0","large":"https://static-cdn.jtvnw.net/emoticons/v1/{image_id}/3.0"},"channels":{"itsyoji":{"title":"ItsYoji","channel_id":"41270990","link":"http://twitch.tv/itsyoji","desc":null,"id":"itsyoji","first_seen":null,"badge":"https://static-cdn.jtvnw.net/jtv_user_pictures/badges/13842/18x18.png","badge_starting":"https://static-cdn.jtvnw.net/jtv_user_pictures/badges/13842/72x72.png","badge_3m":null,"badge_6m":null,"badge_12m":null,"badge_24m":null,"set":16507,"emotes":[{"code":"yojiAmbu","image_id":86885},{"code":"yojiRNG","image_id":89458},{"code":"yojiBoosh","image_id":89690},{"code":"yojiW","image_id":89688},{"code":"yojiFeelsYojiMan","image_id":104755},{"code":"yojiTriggered","image_id":104754}]}}}
