{"template":{"small":"https://static-cdn.jtvnw.net/emoticons/v1/{image_id}/1.0","medium":"https://static-cdn.jtvnw.net/emoticons/v1/{image_id}/2.0","large":"https://static-cdn.jtvnw.net/emoticons/v1/{image_id}/3.0"},"channels":{"jaxerie":{"title":"Jaxerie","channel_id":42426044,"link":"http://twitch.tv/jaxerie","desc":null,"id":"jaxerie","first_seen":null,"badge":"https://static-cdn.jtvnw.net/badges/v1/e5a8c9c8-349c-481b-9ce4-e9197e5f69f5/1","badge_starting":"https://static-cdn.jtvnw.net/badges/v1/e5a8c9c8-349c-481b-9ce4-e9197e5f69f5/3","badge_3m":"https://static-cdn.jtvnw.net/badges/v1/5c6fc962-c2ef-4af7-9250-4b2bdb3d2117/3","badge_6m":"https://static-cdn.jtvnw.net/badges/v1/a772c0d7-42f3-4e22-badf-72b7b4de392b/3","badge_12m":"https://static-cdn.jtvnw.net/badges/v1/105b454d-35a3-4ecc-a12f-d9918e4266b5/3","badge_24m":"https://static-cdn.jtvnw.net/badges/v1/5ec416c7-08d1-4e85-bb91-5dce1ca16001/3","cheermote1":null,"cheermote100":null,"cheermote1000":null,"cheermote5000":null,"cheermote10000":null,"set":5559,"emotes":[{"code":"jaxerPotato","image_id":17507},{"code":"jaxerT","image_id":79757},{"code":"jaxerD","image_id":104376},{"code":"jaxerCool","image_id":133039},{"code":"jaxerRage","image_id":133040},{"code":"jaxerC","image_id":133041}]}}}
