{"template":{"small":"https://static-cdn.jtvnw.net/emoticons/v1/{image_id}/1.0","medium":"https://static-cdn.jtvnw.net/emoticons/v1/{image_id}/2.0","large":"https://static-cdn.jtvnw.net/emoticons/v1/{image_id}/3.0"},"channels":{"johnylemonade":{"title":"JohnyLemonade","channel_id":91108511,"link":"http://twitch.tv/johnylemonade","desc":null,"plans":{"$4.99":"18699","$9.99":"23383","$24.99":"23384"},"id":"johnylemonade","first_seen":"2017-05-20 18:40:03","badge":"https://static-cdn.jtvnw.net/badges/v1/29da627a-54db-4bcc-bb2f-f3e07805fd91/1","badge_starting":"https://static-cdn.jtvnw.net/badges/v1/29da627a-54db-4bcc-bb2f-f3e07805fd91/3","badge_3m":"https://static-cdn.jtvnw.net/badges/v1/d5627a19-ed6b-4666-9ae9-0928bd7e8abb/3","badge_6m":"https://static-cdn.jtvnw.net/badges/v1/7f6ae9c4-0224-4ee4-85dd-646c06205b6c/3","badge_12m":"https://static-cdn.jtvnw.net/badges/v1/c5316462-e846-4d8b-9f99-0bd7baf8c9dc/3","badge_24m":null,"badges":{"0":{"image_url_1x":"https://static-cdn.jtvnw.net/badges/v1/29da627a-54db-4bcc-bb2f-f3e07805fd91/1","image_url_2x":"https://static-cdn.jtvnw.net/badges/v1/29da627a-54db-4bcc-bb2f-f3e07805fd91/2","image_url_4x":"https://static-cdn.jtvnw.net/badges/v1/29da627a-54db-4bcc-bb2f-f3e07805fd91/3","description":"Subscriber","title":"Subscriber","click_action":"subscribe_to_channel","click_url":""},"3":{"image_url_1x":"https://static-cdn.jtvnw.net/badges/v1/d5627a19-ed6b-4666-9ae9-0928bd7e8abb/1","image_url_2x":"https://static-cdn.jtvnw.net/badges/v1/d5627a19-ed6b-4666-9ae9-0928bd7e8abb/2","image_url_4x":"https://static-cdn.jtvnw.net/badges/v1/d5627a19-ed6b-4666-9ae9-0928bd7e8abb/3","description":"3-Month Subscriber","title":"3-Month Subscriber","click_action":"subscribe_to_channel","click_url":""},"6":{"image_url_1x":"https://static-cdn.jtvnw.net/badges/v1/7f6ae9c4-0224-4ee4-85dd-646c06205b6c/1","image_url_2x":"https://static-cdn.jtvnw.net/badges/v1/7f6ae9c4-0224-4ee4-85dd-646c06205b6c/2","image_url_4x":"https://static-cdn.jtvnw.net/badges/v1/7f6ae9c4-0224-4ee4-85dd-646c06205b6c/3","description":"6-Month Subscriber","title":"6-Month Subscriber","click_action":"subscribe_to_channel","click_url":""},"12":{"image_url_1x":"https://static-cdn.jtvnw.net/badges/v1/c5316462-e846-4d8b-9f99-0bd7baf8c9dc/1","image_url_2x":"https://static-cdn.jtvnw.net/badges/v1/c5316462-e846-4d8b-9f99-0bd7baf8c9dc/2","image_url_4x":"https://static-cdn.jtvnw.net/badges/v1/c5316462-e846-4d8b-9f99-0bd7baf8c9dc/3","description":"1-Year Subscriber","title":"1-Year Subscriber","click_action":"subscribe_to_channel","click_url":""}},"bits_badges":null,"cheermote1":null,"cheermote100":null,"cheermote1000":null,"cheermote5000":null,"cheermote10000":null,"set":23383,"emotes":[{"code":"jlmndFace","image_id":192303,"set":23383},{"code":"jlmndHype","image_id":112782,"set":18699},{"code":"jlmndLove","image_id":135784,"set":18699},{"code":"jlmndWow","image_id":112784,"set":18699},{"code":"jlmndLol","image_id":143108,"set":18699},{"code":"jlmndCry","image_id":113661,"set":18699},{"code":"jlmndPride","image_id":190567,"set":18699},{"code":"jlmndHello","image_id":137162,"set":18699},{"code":"jlmndCool","image_id":135783,"set":18699},{"code":"jlmndRage","image_id":128793,"set":18699},{"code":"jlmndPeach","image_id":216432,"set":23384},{"code":"jlmndBolid","image_id":216393,"set":18699}]}}}
