{"template":{"small":"https://static-cdn.jtvnw.net/emoticons/v1/{image_id}/1.0","medium":"https://static-cdn.jtvnw.net/emoticons/v1/{image_id}/2.0","large":"https://static-cdn.jtvnw.net/emoticons/v1/{image_id}/3.0"},"channels":{"jonsandman":{"title":"JonSandman","channel_id":47034673,"link":"http://twitch.tv/jonsandman","desc":null,"id":"jonsandman","first_seen":null,"badge":"https://static-cdn.jtvnw.net/badges/v1/8aba71e1-db75-445b-aa53-c503a66814a3/1","badge_starting":"https://static-cdn.jtvnw.net/badges/v1/8aba71e1-db75-445b-aa53-c503a66814a3/3","badge_3m":"https://static-cdn.jtvnw.net/badges/v1/1871794a-e240-4a7f-adfe-74f38d248c0b/3","badge_6m":"https://static-cdn.jtvnw.net/badges/v1/81c89746-f969-4590-89eb-3789fb153f4f/3","badge_12m":"https://static-cdn.jtvnw.net/badges/v1/6cb29dae-6af9-42a2-a805-e3075784f69d/3","badge_24m":"https://static-cdn.jtvnw.net/badges/v1/6cc44e88-fa88-4fe4-b7b6-b76ca069dc28/3","cheermote1":null,"cheermote100":null,"cheermote1000":null,"cheermote5000":null,"cheermote10000":null,"set":8084,"emotes":[{"code":"sandmanREKT","image_id":25929},{"code":"sandmanSHOT","image_id":25044},{"code":"sandmanHYPE","image_id":25146},{"code":"sandmanLOVE","image_id":26925},{"code":"sandmanMONEY","image_id":26930},{"code":"sandmanTD","image_id":27684},{"code":"sandmanRIP","image_id":28184},{"code":"sandmanHA","image_id":33221},{"code":"sandmanFACE","image_id":33216},{"code":"sandmanCHAMP","image_id":105892},{"code":"sandmanMAYO","image_id":105891},{"code":"sandmanMERLIN","image_id":105890},{"code":"sandmanCHAIR","image_id":105889},{"code":"sandmanDANCE","image_id":69590},{"code":"sandmanCRINGE","image_id":70549},{"code":"sandmanHEY5","image_id":70550},{"code":"sandmanARMY","image_id":79498},{"code":"sandmanPOTATO","image_id":158943},{"code":"sandmanFEELS","image_id":105934},{"code":"sandmanROB","image_id":107207}]}}}
