{"template":{"small":"https://static-cdn.jtvnw.net/emoticons/v1/{image_id}/1.0","medium":"https://static-cdn.jtvnw.net/emoticons/v1/{image_id}/2.0","large":"https://static-cdn.jtvnw.net/emoticons/v1/{image_id}/3.0"},"channels":{"klutch":{"title":"Klutch","channel_id":"6353604","link":"http://twitch.tv/klutch","desc":null,"id":"klutch","first_seen":"2016-05-23 09:35:04","badge":"https://static-cdn.jtvnw.net/jtv_user_pictures/badges/13064/18x18.png","badge_starting":"https://static-cdn.jtvnw.net/jtv_user_pictures/badges/13064/72x72.png","badge_3m":null,"badge_6m":null,"badge_12m":null,"badge_24m":null,"set":15886,"emotes":[{"code":"klutchIlluminati","image_id":100092},{"code":"klutchEnough","image_id":81454},{"code":"klutchHype","image_id":101686},{"code":"klutchWat","image_id":101687},{"code":"klutchHello","image_id":100972},{"code":"klutchSus","image_id":115803}]}}}
