{"template":{"small":"https://static-cdn.jtvnw.net/emoticons/v1/{image_id}/1.0","medium":"https://static-cdn.jtvnw.net/emoticons/v1/{image_id}/2.0","large":"https://static-cdn.jtvnw.net/emoticons/v1/{image_id}/3.0"},"channels":{"lazycattv":{"title":"LazycatTV","channel_id":74662686,"link":"http://twitch.tv/lazycattv","desc":null,"plans":{"$4.99":"178307","$9.99":"178310","$24.99":"178311"},"id":"lazycattv","first_seen":"2017-07-03 21:05:28","badge":null,"badge_starting":null,"badge_3m":null,"badge_6m":null,"badge_12m":null,"badge_24m":null,"badges":null,"bits_badges":null,"cheermote1":null,"cheermote100":null,"cheermote1000":null,"cheermote5000":null,"cheermote10000":null,"set":178311,"emotes":[{"code":"lazycaLALA","image_id":228172,"set":178311},{"code":"lazycaLCGLH","image_id":228313,"set":178310},{"code":"lazycaLazyheart","image_id":227765,"set":178307}]}}}
