{"template":{"small":"https://static-cdn.jtvnw.net/emoticons/v1/{image_id}/1.0","medium":"https://static-cdn.jtvnw.net/emoticons/v1/{image_id}/2.0","large":"https://static-cdn.jtvnw.net/emoticons/v1/{image_id}/3.0"},"channels":{"letsmakefriends":{"title":"letsmakefriends","channel_id":"71485748","link":"http://twitch.tv/letsmakefriends","desc":null,"id":"letsmakefriends","first_seen":null,"badge":"https://static-cdn.jtvnw.net/badges/v1/36561ce0-a62b-4ae6-ab24-1e5b3f3779d3/1","badge_starting":"https://static-cdn.jtvnw.net/badges/v1/36561ce0-a62b-4ae6-ab24-1e5b3f3779d3/3","badge_3m":"https://static-cdn.jtvnw.net/badges/v1/9a5e1367-b296-409c-9a10-7856dc04ad86/3","badge_6m":"https://static-cdn.jtvnw.net/badges/v1/bb6711a4-cf96-4b20-9c6b-558a6fdb9fc7/3","badge_12m":"https://static-cdn.jtvnw.net/badges/v1/10b9c17a-01f1-463d-91ff-73f244233fb4/3","badge_24m":null,"set":13622,"emotes":[{"code":"letsRage","image_id":58154},{"code":"letsPog","image_id":58155},{"code":"letsCandle","image_id":55045},{"code":"letsSmile","image_id":55046},{"code":"letsThump","image_id":59184},{"code":"letsKappa","image_id":63396},{"code":"letsLobe","image_id":71403},{"code":"letsPheebs","image_id":105041},{"code":"letsBlush","image_id":105045},{"code":"letsLUL","image_id":108026}]}}}
