{"template":{"small":"https://static-cdn.jtvnw.net/emoticons/v1/{image_id}/1.0","medium":"https://static-cdn.jtvnw.net/emoticons/v1/{image_id}/2.0","large":"https://static-cdn.jtvnw.net/emoticons/v1/{image_id}/3.0"},"channels":{"ltzonda":{"title":"Ltzonda","channel_id":12943124,"link":"http://twitch.tv/ltzonda","desc":null,"plans":{"$4.99":"4589","$9.99":"24625","$24.99":"24626"},"id":"ltzonda","first_seen":null,"badge":"https://static-cdn.jtvnw.net/badges/v1/ac84dec5-0d0d-420d-b5fe-05fa7c7022a1/1","badge_starting":"https://static-cdn.jtvnw.net/badges/v1/ac84dec5-0d0d-420d-b5fe-05fa7c7022a1/3","badge_3m":"https://static-cdn.jtvnw.net/badges/v1/799bd54e-b647-4bbb-8a5c-180c8506173e/3","badge_6m":"https://static-cdn.jtvnw.net/badges/v1/106aeec3-72f7-4dd4-bdf9-d171adcc76e0/3","badge_12m":"https://static-cdn.jtvnw.net/badges/v1/d49b4a13-03ce-4683-880e-0fd6ab6ea0d7/3","badge_24m":"https://static-cdn.jtvnw.net/badges/v1/62dec233-8b92-4818-830b-cffb237770d0/3","badges":{"0":{"image_url_1x":"https://static-cdn.jtvnw.net/badges/v1/ac84dec5-0d0d-420d-b5fe-05fa7c7022a1/1","image_url_2x":"https://static-cdn.jtvnw.net/badges/v1/ac84dec5-0d0d-420d-b5fe-05fa7c7022a1/2","image_url_4x":"https://static-cdn.jtvnw.net/badges/v1/ac84dec5-0d0d-420d-b5fe-05fa7c7022a1/3","description":"Subscriber","title":"Subscriber","click_action":"subscribe_to_channel","click_url":""},"3":{"image_url_1x":"https://static-cdn.jtvnw.net/badges/v1/799bd54e-b647-4bbb-8a5c-180c8506173e/1","image_url_2x":"https://static-cdn.jtvnw.net/badges/v1/799bd54e-b647-4bbb-8a5c-180c8506173e/2","image_url_4x":"https://static-cdn.jtvnw.net/badges/v1/799bd54e-b647-4bbb-8a5c-180c8506173e/3","description":"3-Month Subscriber","title":"3-Month Subscriber","click_action":"subscribe_to_channel","click_url":""},"6":{"image_url_1x":"https://static-cdn.jtvnw.net/badges/v1/106aeec3-72f7-4dd4-bdf9-d171adcc76e0/1","image_url_2x":"https://static-cdn.jtvnw.net/badges/v1/106aeec3-72f7-4dd4-bdf9-d171adcc76e0/2","image_url_4x":"https://static-cdn.jtvnw.net/badges/v1/106aeec3-72f7-4dd4-bdf9-d171adcc76e0/3","description":"6-Month Subscriber","title":"6-Month Subscriber","click_action":"subscribe_to_channel","click_url":""},"12":{"image_url_1x":"https://static-cdn.jtvnw.net/badges/v1/d49b4a13-03ce-4683-880e-0fd6ab6ea0d7/1","image_url_2x":"https://static-cdn.jtvnw.net/badges/v1/d49b4a13-03ce-4683-880e-0fd6ab6ea0d7/2","image_url_4x":"https://static-cdn.jtvnw.net/badges/v1/d49b4a13-03ce-4683-880e-0fd6ab6ea0d7/3","description":"1-Year Subscriber","title":"1-Year Subscriber","click_action":"subscribe_to_channel","click_url":""},"24":{"image_url_1x":"https://static-cdn.jtvnw.net/badges/v1/62dec233-8b92-4818-830b-cffb237770d0/1","image_url_2x":"https://static-cdn.jtvnw.net/badges/v1/62dec233-8b92-4818-830b-cffb237770d0/2","image_url_4x":"https://static-cdn.jtvnw.net/badges/v1/62dec233-8b92-4818-830b-cffb237770d0/3","description":"2-Year Subscriber","title":"2-Year Subscriber","click_action":"subscribe_to_channel","click_url":""}},"bits_badges":null,"cheermote1":null,"cheermote100":null,"cheermote1000":null,"cheermote5000":null,"cheermote10000":null,"set":4589,"emotes":[{"code":"zondaTroll","image_id":17349,"set":4589},{"code":"zondaLove","image_id":19507,"set":4589},{"code":"zondaCreep","image_id":31277,"set":4589},{"code":"zondaHeyGirls","image_id":51348,"set":4589},{"code":"zondaSellOut","image_id":51443,"set":4589},{"code":"zondaTRIGGERED","image_id":119904,"set":4589},{"code":"zondaGasm","image_id":121176,"set":4589},{"code":"zondaHug","image_id":193137,"set":4589},{"code":"zondaDead","image_id":168271,"set":4589},{"code":"zondaCS","image_id":155032,"set":4589},{"code":"zondaSCLOVE","image_id":155034,"set":4589},{"code":"zondaRAGE","image_id":176776,"set":4589},{"code":"zondaYes","image_id":155586,"set":4589},{"code":"zondaAww","image_id":180254,"set":4589},{"code":"zondaFeelsBad","image_id":200985,"set":24625},{"code":"zondaFeelsGood","image_id":200986,"set":24626},{"code":"zondaSenpai","image_id":200987,"set":4589},{"code":"zondaHYPE","image_id":236113,"set":4589},{"code":"zondaFat","image_id":236134,"set":4589},{"code":"zondaLUL","image_id":197533,"set":4589},{"code":"zondaDafuq","image_id":197543,"set":4589},{"code":"zondaNose","image_id":197548,"set":4589}]}}}
