{"template":{"small":"https://static-cdn.jtvnw.net/emoticons/v1/{image_id}/1.0","medium":"https://static-cdn.jtvnw.net/emoticons/v1/{image_id}/2.0","large":"https://static-cdn.jtvnw.net/emoticons/v1/{image_id}/3.0"},"channels":{"mendokusaii":{"title":"mendokusaii","channel_id":57717183,"link":"http://twitch.tv/mendokusaii","desc":null,"plans":{"$4.99":"16357","$9.99":"27960","$24.99":"27961"},"id":"mendokusaii","first_seen":"2016-12-01 11:55:03","badge":"https://static-cdn.jtvnw.net/badges/v1/d8639c27-b9e1-42fe-b2c2-5972729697ac/1","badge_starting":"https://static-cdn.jtvnw.net/badges/v1/d8639c27-b9e1-42fe-b2c2-5972729697ac/3","badge_3m":"https://static-cdn.jtvnw.net/badges/v1/4e7d3ada-3f3e-4ef3-b011-a7b53cfa92c8/3","badge_6m":"https://static-cdn.jtvnw.net/badges/v1/8542bda2-8218-4310-b3e6-bf72e04644da/3","badge_12m":"https://static-cdn.jtvnw.net/badges/v1/d2949544-920b-4527-a953-b781b4a18fa3/3","badge_24m":null,"cheermote1":null,"cheermote100":null,"cheermote1000":null,"cheermote5000":null,"cheermote10000":null,"set":16357,"emotes":[{"code":"mendoLUL","image_id":130711,"set":16357},{"code":"mendoCat","image_id":85638,"set":16357},{"code":"mendoCry","image_id":132619,"set":16357},{"code":"mendoP","image_id":89596,"set":16357},{"code":"mendoM","image_id":90864,"set":16357},{"code":"mendoBlush","image_id":111693,"set":16357},{"code":"mendoWeeb","image_id":105480,"set":16357},{"code":"mendoLewd","image_id":108286,"set":16357},{"code":"mendoXD","image_id":111696,"set":16357},{"code":"mendoTemp","image_id":131336,"set":16357},{"code":"mendoDva","image_id":131338,"set":16357},{"code":"mendoBeta","image_id":139293,"set":16357},{"code":"mendoLilac","image_id":139294,"set":16357},{"code":"mendoPuke","image_id":139295,"set":16357},{"code":"mendoC9","image_id":123908,"set":16357},{"code":"mendoE","image_id":124498,"set":16357},{"code":"mendoYea","image_id":124820,"set":16357},{"code":"mendoNana","image_id":139296,"set":16357},{"code":"mendoNewd","image_id":139297,"set":16357},{"code":"mendoSame","image_id":125611,"set":16357}]}}}
