{"template":{"small":"https://static-cdn.jtvnw.net/emoticons/v1/{image_id}/1.0","medium":"https://static-cdn.jtvnw.net/emoticons/v1/{image_id}/2.0","large":"https://static-cdn.jtvnw.net/emoticons/v1/{image_id}/3.0"},"channels":{"phoebina":{"title":"Phoebina","channel_id":39184490,"link":"http://twitch.tv/phoebina","desc":null,"plans":{"$4.99":"57232","$9.99":"57233","$24.99":"57234"},"id":"phoebina","first_seen":"2017-06-21 02:30:08","badge":"https://static-cdn.jtvnw.net/badges/v1/54ed80b5-4154-4b3b-bc91-166dfa95d4af/1","badge_starting":"https://static-cdn.jtvnw.net/badges/v1/54ed80b5-4154-4b3b-bc91-166dfa95d4af/3","badge_3m":"https://static-cdn.jtvnw.net/badges/v1/c797b995-8965-4685-b3e2-4004ee537c38/3","badge_6m":"https://static-cdn.jtvnw.net/badges/v1/c9a79828-27d9-41d9-962c-d0207665e1bb/3","badge_12m":"https://static-cdn.jtvnw.net/badges/v1/2591afce-3717-4553-9ce2-bf512871a006/3","badge_24m":"https://static-cdn.jtvnw.net/badges/v1/9aa9fd9b-f52a-4c6b-a408-b03b3f4d2f2c/3","badges":{"0":{"image_url_1x":"https://static-cdn.jtvnw.net/badges/v1/54ed80b5-4154-4b3b-bc91-166dfa95d4af/1","image_url_2x":"https://static-cdn.jtvnw.net/badges/v1/54ed80b5-4154-4b3b-bc91-166dfa95d4af/2","image_url_4x":"https://static-cdn.jtvnw.net/badges/v1/54ed80b5-4154-4b3b-bc91-166dfa95d4af/3","description":"Subscriber","title":"Subscriber","click_action":"subscribe_to_channel","click_url":""},"3":{"image_url_1x":"https://static-cdn.jtvnw.net/badges/v1/c797b995-8965-4685-b3e2-4004ee537c38/1","image_url_2x":"https://static-cdn.jtvnw.net/badges/v1/c797b995-8965-4685-b3e2-4004ee537c38/2","image_url_4x":"https://static-cdn.jtvnw.net/badges/v1/c797b995-8965-4685-b3e2-4004ee537c38/3","description":"3-Month Subscriber","title":"3-Month Subscriber","click_action":"subscribe_to_channel","click_url":""},"6":{"image_url_1x":"https://static-cdn.jtvnw.net/badges/v1/c9a79828-27d9-41d9-962c-d0207665e1bb/1","image_url_2x":"https://static-cdn.jtvnw.net/badges/v1/c9a79828-27d9-41d9-962c-d0207665e1bb/2","image_url_4x":"https://static-cdn.jtvnw.net/badges/v1/c9a79828-27d9-41d9-962c-d0207665e1bb/3","description":"6-Month Subscriber","title":"6-Month Subscriber","click_action":"subscribe_to_channel","click_url":""},"12":{"image_url_1x":"https://static-cdn.jtvnw.net/badges/v1/2591afce-3717-4553-9ce2-bf512871a006/1","image_url_2x":"https://static-cdn.jtvnw.net/badges/v1/2591afce-3717-4553-9ce2-bf512871a006/2","image_url_4x":"https://static-cdn.jtvnw.net/badges/v1/2591afce-3717-4553-9ce2-bf512871a006/3","description":"1-Year Subscriber","title":"1-Year Subscriber","click_action":"subscribe_to_channel","click_url":""},"24":{"image_url_1x":"https://static-cdn.jtvnw.net/badges/v1/9aa9fd9b-f52a-4c6b-a408-b03b3f4d2f2c/1","image_url_2x":"https://static-cdn.jtvnw.net/badges/v1/9aa9fd9b-f52a-4c6b-a408-b03b3f4d2f2c/2","image_url_4x":"https://static-cdn.jtvnw.net/badges/v1/9aa9fd9b-f52a-4c6b-a408-b03b3f4d2f2c/3","description":"2-Year Subscriber","title":"2-Year Subscriber","click_action":"subscribe_to_channel","click_url":""}},"bits_badges":null,"cheermote1":null,"cheermote100":null,"cheermote1000":null,"cheermote5000":null,"cheermote10000":null,"set":57232,"emotes":[{"code":"phoeRp","image_id":211110,"set":57232},{"code":"phoeFan","image_id":211092,"set":57232},{"code":"phoeRa","image_id":211100,"set":57232},{"code":"phoeCorn","image_id":211105,"set":57232},{"code":"phoeCasper","image_id":211112,"set":57232},{"code":"phoeCry","image_id":265585,"set":57232},{"code":"phoeKap","image_id":210388,"set":57232},{"code":"phoePalm","image_id":206072,"set":57232},{"code":"phoeKing","image_id":206105,"set":57234},{"code":"phoePepellidan","image_id":206107,"set":57233},{"code":"phoeRofl","image_id":273238,"set":57232},{"code":"phoeDZ","image_id":290864,"set":57232},{"code":"phoeHype","image_id":273645,"set":57232}]}}}
