{"template":{"small":"https://static-cdn.jtvnw.net/emoticons/v1/{image_id}/1.0","medium":"https://static-cdn.jtvnw.net/emoticons/v1/{image_id}/2.0","large":"https://static-cdn.jtvnw.net/emoticons/v1/{image_id}/3.0"},"channels":{"r3solv3_gaming":{"title":"r3solv3_gaming","channel_id":48603590,"link":"http://twitch.tv/r3solv3_gaming","desc":null,"plans":{"$4.99":"212237","$9.99":"212239","$24.99":"212240"},"id":"r3solv3_gaming","first_seen":"2017-06-29 22:20:10","badge":null,"badge_starting":null,"badge_3m":null,"badge_6m":null,"badge_12m":null,"badge_24m":null,"badges":null,"bits_badges":null,"cheermote1":null,"cheermote100":null,"cheermote1000":null,"cheermote5000":null,"cheermote10000":null,"set":212237,"emotes":[{"code":"r3solvLove","image_id":245026,"set":212237},{"code":"r3solvHype","image_id":245030,"set":212239}]}}}
