{"template":{"small":"https://static-cdn.jtvnw.net/emoticons/v1/{image_id}/1.0","medium":"https://static-cdn.jtvnw.net/emoticons/v1/{image_id}/2.0","large":"https://static-cdn.jtvnw.net/emoticons/v1/{image_id}/3.0"},"channels":{"reapered":{"title":"Reapered","channel_id":32119442,"link":"http://twitch.tv/reapered","desc":null,"id":"reapered","first_seen":null,"badge":"https://static-cdn.jtvnw.net/badges/v1/f8bdf951-c0f9-4f4c-bac1-6126e8d58967/1","badge_starting":"https://static-cdn.jtvnw.net/badges/v1/f8bdf951-c0f9-4f4c-bac1-6126e8d58967/3","badge_3m":null,"badge_6m":null,"badge_12m":null,"badge_24m":null,"set":16496,"emotes":[{"code":"ltkLTKB","image_id":89832},{"code":"ltkLabpered","image_id":89831}]}}}
