{"template":{"small":"https://static-cdn.jtvnw.net/emoticons/v1/{image_id}/1.0","medium":"https://static-cdn.jtvnw.net/emoticons/v1/{image_id}/2.0","large":"https://static-cdn.jtvnw.net/emoticons/v1/{image_id}/3.0"},"channels":{"revoluti8n":{"title":"Revoluti8n","channel_id":21592077,"link":"http://twitch.tv/revoluti8n","desc":null,"plans":{"$4.99":"17520","$9.99":"35262","$24.99":"35263"},"id":"revoluti8n","first_seen":"2016-06-23 12:40:03","badge":"https://static-cdn.jtvnw.net/badges/v1/aff63ea3-1ab3-467e-aaf9-a4cf3694d9dd/1","badge_starting":"https://static-cdn.jtvnw.net/badges/v1/aff63ea3-1ab3-467e-aaf9-a4cf3694d9dd/3","badge_3m":null,"badge_6m":null,"badge_12m":null,"badge_24m":null,"badges":[{"image_url_1x":"https://static-cdn.jtvnw.net/badges/v1/aff63ea3-1ab3-467e-aaf9-a4cf3694d9dd/1","image_url_2x":"https://static-cdn.jtvnw.net/badges/v1/aff63ea3-1ab3-467e-aaf9-a4cf3694d9dd/2","image_url_4x":"https://static-cdn.jtvnw.net/badges/v1/aff63ea3-1ab3-467e-aaf9-a4cf3694d9dd/3","description":"Subscriber","title":"Subscriber","click_action":"subscribe_to_channel","click_url":""}],"bits_badges":null,"cheermote1":null,"cheermote100":null,"cheermote1000":null,"cheermote5000":null,"cheermote10000":null,"set":17520,"emotes":[{"code":"revoluti8nDubrica","image_id":103804,"set":17520}]}}}
