{"template":{"small":"https://static-cdn.jtvnw.net/emoticons/v1/{image_id}/1.0","medium":"https://static-cdn.jtvnw.net/emoticons/v1/{image_id}/2.0","large":"https://static-cdn.jtvnw.net/emoticons/v1/{image_id}/3.0"},"channels":{"sjdml22":{"title":"sjdml22","channel_id":29350822,"link":"http://twitch.tv/sjdml22","desc":null,"plans":{"$4.99":"19929","$9.99":"37880","$24.99":"37881"},"id":"sjdml22","first_seen":"2017-02-09 16:40:05","badge":null,"badge_starting":null,"badge_3m":null,"badge_6m":null,"badge_12m":null,"badge_24m":null,"badges":null,"bits_badges":null,"cheermote1":null,"cheermote100":null,"cheermote1000":null,"cheermote5000":null,"cheermote10000":null,"set":19929,"emotes":[{"code":"scscDd","image_id":147588,"set":19929}]}}}
