{"template":{"small":"https://static-cdn.jtvnw.net/emoticons/v1/{image_id}/1.0","medium":"https://static-cdn.jtvnw.net/emoticons/v1/{image_id}/2.0","large":"https://static-cdn.jtvnw.net/emoticons/v1/{image_id}/3.0"},"channels":{"snitchhhhh":{"title":"Snitchhhhh","channel_id":"31482482","link":"http://twitch.tv/snitchhhhh","desc":null,"id":"snitchhhhh","first_seen":null,"badge":"https://static-cdn.jtvnw.net/badges/v1/9e2a1f2d-0de1-4fb9-993f-bdb8d752483a/1","badge_starting":"https://static-cdn.jtvnw.net/badges/v1/9e2a1f2d-0de1-4fb9-993f-bdb8d752483a/3","badge_3m":null,"badge_6m":null,"badge_12m":null,"badge_24m":null,"set":13022,"emotes":[{"code":"snitchSSD","image_id":49604},{"code":"snitchW","image_id":91341}]}}}
