{"template":{"small":"https://static-cdn.jtvnw.net/emoticons/v1/{image_id}/1.0","medium":"https://static-cdn.jtvnw.net/emoticons/v1/{image_id}/2.0","large":"https://static-cdn.jtvnw.net/emoticons/v1/{image_id}/3.0"},"channels":{"starlightskyes":{"title":"StarlightSkyes","channel_id":61995577,"link":"http://twitch.tv/starlightskyes","desc":null,"plans":{"$4.99":"18206","$9.99":"24019","$24.99":"24020"},"id":"starlightskyes","first_seen":"2017-05-01 13:20:03","badge":"https://static-cdn.jtvnw.net/badges/v1/74b38ea4-0c47-4c86-8790-08d929cd55cc/1","badge_starting":"https://static-cdn.jtvnw.net/badges/v1/74b38ea4-0c47-4c86-8790-08d929cd55cc/3","badge_3m":"https://static-cdn.jtvnw.net/badges/v1/3c80d4ed-1be8-47ab-afa5-b998419ef6e3/3","badge_6m":"https://static-cdn.jtvnw.net/badges/v1/a23aa2f4-2049-4196-a2d1-c2d40f1e6090/3","badge_12m":"https://static-cdn.jtvnw.net/badges/v1/a510c513-46c0-4313-b475-86423cb7037a/3","badge_24m":"https://static-cdn.jtvnw.net/badges/v1/9ad40992-bff8-49d7-9dfc-89eb42d77b11/3","cheermote1":null,"cheermote100":null,"cheermote1000":null,"cheermote5000":null,"cheermote10000":null,"set":18206,"emotes":[{"code":"starrPet","image_id":178531,"set":18206},{"code":"starrLife","image_id":178605,"set":18206},{"code":"starrHey","image_id":178609,"set":18206},{"code":"starrShy","image_id":178547,"set":24019},{"code":"starrSad","image_id":178617,"set":18206},{"code":"starrRip","image_id":178620,"set":18206},{"code":"starrHype","image_id":178621,"set":18206},{"code":"starrWow","image_id":178564,"set":24020}]}}}
