{"template":{"small":"https://static-cdn.jtvnw.net/emoticons/v1/{image_id}/1.0","medium":"https://static-cdn.jtvnw.net/emoticons/v1/{image_id}/2.0","large":"https://static-cdn.jtvnw.net/emoticons/v1/{image_id}/3.0"},"channels":{"superdadheroics":{"title":"superdadheroics","channel_id":115799302,"link":"http://twitch.tv/superdadheroics","desc":null,"plans":{"$4.99":"151639","$9.99":"151640","$24.99":"151641"},"id":"superdadheroics","first_seen":"2017-07-01 22:35:04","badge":null,"badge_starting":null,"badge_3m":null,"badge_6m":null,"badge_12m":null,"badge_24m":null,"badges":null,"bits_badges":null,"cheermote1":null,"cheermote100":null,"cheermote1000":null,"cheermote5000":null,"cheermote10000":null,"set":151640,"emotes":[{"code":"superd2DadsGottem","image_id":254271,"set":151640},{"code":"superd2DadsBeast","image_id":254285,"set":151641},{"code":"superd2Dad","image_id":242543,"set":151639}]}}}
