{"template":{"small":"https://static-cdn.jtvnw.net/emoticons/v1/{image_id}/1.0","medium":"https://static-cdn.jtvnw.net/emoticons/v1/{image_id}/2.0","large":"https://static-cdn.jtvnw.net/emoticons/v1/{image_id}/3.0"},"channels":{"troydangaming":{"title":"TroydanGaming","channel_id":48478126,"link":"http://twitch.tv/troydangaming","desc":null,"plans":{"$4.99":"5464","$9.99":"43696","$24.99":"43697"},"id":"troydangaming","first_seen":null,"badge":"https://static-cdn.jtvnw.net/badges/v1/f1fd4def-fe1c-44ec-851b-2d50a6db4601/1","badge_starting":"https://static-cdn.jtvnw.net/badges/v1/f1fd4def-fe1c-44ec-851b-2d50a6db4601/3","badge_3m":"https://static-cdn.jtvnw.net/badges/v1/75fa7f43-a2fd-4927-8895-b644c34ee501/3","badge_6m":"https://static-cdn.jtvnw.net/badges/v1/1dfff6b0-e9df-4ac4-9ea4-d8a187158677/3","badge_12m":"https://static-cdn.jtvnw.net/badges/v1/bef69bb0-e851-4941-a1b6-4c4c61c3e127/3","badge_24m":"https://static-cdn.jtvnw.net/badges/v1/d591311f-f122-4e32-934f-47a36e6966be/3","badges":{"0":{"image_url_1x":"https://static-cdn.jtvnw.net/badges/v1/f1fd4def-fe1c-44ec-851b-2d50a6db4601/1","image_url_2x":"https://static-cdn.jtvnw.net/badges/v1/f1fd4def-fe1c-44ec-851b-2d50a6db4601/2","image_url_4x":"https://static-cdn.jtvnw.net/badges/v1/f1fd4def-fe1c-44ec-851b-2d50a6db4601/3","description":"Subscriber","title":"Subscriber","click_action":"subscribe_to_channel","click_url":""},"3":{"image_url_1x":"https://static-cdn.jtvnw.net/badges/v1/75fa7f43-a2fd-4927-8895-b644c34ee501/1","image_url_2x":"https://static-cdn.jtvnw.net/badges/v1/75fa7f43-a2fd-4927-8895-b644c34ee501/2","image_url_4x":"https://static-cdn.jtvnw.net/badges/v1/75fa7f43-a2fd-4927-8895-b644c34ee501/3","description":"3-Month Subscriber","title":"3-Month Subscriber","click_action":"subscribe_to_channel","click_url":""},"6":{"image_url_1x":"https://static-cdn.jtvnw.net/badges/v1/1dfff6b0-e9df-4ac4-9ea4-d8a187158677/1","image_url_2x":"https://static-cdn.jtvnw.net/badges/v1/1dfff6b0-e9df-4ac4-9ea4-d8a187158677/2","image_url_4x":"https://static-cdn.jtvnw.net/badges/v1/1dfff6b0-e9df-4ac4-9ea4-d8a187158677/3","description":"6-Month Subscriber","title":"6-Month Subscriber","click_action":"subscribe_to_channel","click_url":""},"12":{"image_url_1x":"https://static-cdn.jtvnw.net/badges/v1/bef69bb0-e851-4941-a1b6-4c4c61c3e127/1","image_url_2x":"https://static-cdn.jtvnw.net/badges/v1/bef69bb0-e851-4941-a1b6-4c4c61c3e127/2","image_url_4x":"https://static-cdn.jtvnw.net/badges/v1/bef69bb0-e851-4941-a1b6-4c4c61c3e127/3","description":"1-Year Subscriber","title":"1-Year Subscriber","click_action":"subscribe_to_channel","click_url":""},"24":{"image_url_1x":"https://static-cdn.jtvnw.net/badges/v1/d591311f-f122-4e32-934f-47a36e6966be/1","image_url_2x":"https://static-cdn.jtvnw.net/badges/v1/d591311f-f122-4e32-934f-47a36e6966be/2","image_url_4x":"https://static-cdn.jtvnw.net/badges/v1/d591311f-f122-4e32-934f-47a36e6966be/3","description":"2-Year Subscriber","title":"2-Year Subscriber","click_action":"subscribe_to_channel","click_url":""}},"bits_badges":null,"cheermote1":null,"cheermote100":null,"cheermote1000":null,"cheermote5000":null,"cheermote10000":null,"set":5464,"emotes":[{"code":"troydanHype","image_id":33338,"set":5464},{"code":"troydanWut","image_id":102297,"set":5464},{"code":"troydanFail","image_id":53770,"set":5464},{"code":"troydanRage","image_id":17271,"set":5464},{"code":"troydanButton","image_id":19565,"set":5464},{"code":"troydanHeart","image_id":21945,"set":5464},{"code":"troydanSmile","image_id":67828,"set":5464},{"code":"troydanShh","image_id":38524,"set":5464},{"code":"troydanGasm","image_id":77994,"set":5464},{"code":"troydanPoop","image_id":57080,"set":5464},{"code":"troydanYousuck","image_id":57079,"set":5464},{"code":"troydanRIP","image_id":57078,"set":5464},{"code":"troydanBye","image_id":57077,"set":5464},{"code":"troydanGG","image_id":75742,"set":5464},{"code":"troydanSwaggy","image_id":189569,"set":5464},{"code":"troydanDerp","image_id":78337,"set":5464},{"code":"troydan1","image_id":106807,"set":5464},{"code":"troydanShook","image_id":104250,"set":5464},{"code":"troydanGreen","image_id":114958,"set":5464},{"code":"troydanCringe","image_id":137508,"set":5464},{"code":"troydanOh","image_id":137934,"set":5464},{"code":"troydanJazz","image_id":179025,"set":5464},{"code":"troydanStoner","image_id":179029,"set":5464},{"code":"troydanPride","image_id":179229,"set":5464},{"code":"troydanKobe","image_id":179032,"set":5464},{"code":"troydanSqueaker","image_id":179383,"set":5464},{"code":"troydanShaq","image_id":181073,"set":5464},{"code":"troydanUh","image_id":171260,"set":5464},{"code":"troydanJimmy","image_id":171270,"set":5464},{"code":"troydanEgg","image_id":171312,"set":5464},{"code":"troydanDut","image_id":171293,"set":5464},{"code":"troydanThumb","image_id":171284,"set":5464},{"code":"troydanWhy","image_id":171290,"set":5464},{"code":"troydanGary","image_id":184897,"set":5464},{"code":"troydanDown","image_id":187167,"set":5464}]}}}
