{"template":{"small":"https://static-cdn.jtvnw.net/emoticons/v1/{image_id}/1.0","medium":"https://static-cdn.jtvnw.net/emoticons/v1/{image_id}/2.0","large":"https://static-cdn.jtvnw.net/emoticons/v1/{image_id}/3.0"},"channels":{"twosync":{"title":"TwoSync","channel_id":39446058,"link":"http://twitch.tv/twosync","desc":null,"plans":{"$4.99":"14519","$9.99":"41026","$24.99":"41027"},"id":"twosync","first_seen":null,"badge":"https://static-cdn.jtvnw.net/badges/v1/2ea80698-7091-4b11-b395-0245bbfac9f1/1","badge_starting":"https://static-cdn.jtvnw.net/badges/v1/2ea80698-7091-4b11-b395-0245bbfac9f1/3","badge_3m":null,"badge_6m":null,"badge_12m":null,"badge_24m":null,"badges":[{"image_url_1x":"https://static-cdn.jtvnw.net/badges/v1/2ea80698-7091-4b11-b395-0245bbfac9f1/1","image_url_2x":"https://static-cdn.jtvnw.net/badges/v1/2ea80698-7091-4b11-b395-0245bbfac9f1/2","image_url_4x":"https://static-cdn.jtvnw.net/badges/v1/2ea80698-7091-4b11-b395-0245bbfac9f1/3","description":"Subscriber","title":"Subscriber","click_action":"subscribe_to_channel","click_url":""}],"bits_badges":null,"cheermote1":null,"cheermote100":null,"cheermote1000":null,"cheermote5000":null,"cheermote10000":null,"set":14519,"emotes":[{"code":"syncPump","image_id":63954,"set":14519},{"code":"syncSquad","image_id":63955,"set":14519},{"code":"syncChris","image_id":63744,"set":14519},{"code":"syncMat","image_id":63742,"set":14519},{"code":"syncSick","image_id":64358,"set":14519},{"code":"syncSync","image_id":64354,"set":14519},{"code":"syncWhata","image_id":64352,"set":14519},{"code":"syncPalm","image_id":64351,"set":14519}]}}}
