{"template":{"small":"https://static-cdn.jtvnw.net/emoticons/v1/{image_id}/1.0","medium":"https://static-cdn.jtvnw.net/emoticons/v1/{image_id}/2.0","large":"https://static-cdn.jtvnw.net/emoticons/v1/{image_id}/3.0"},"channels":{"youyoud2":{"title":"Youyoud2","channel_id":"41727944","link":"http://twitch.tv/youyoud2","desc":null,"id":"youyoud2","first_seen":"2016-03-27 02:00:03","badge":"https://static-cdn.jtvnw.net/jtv_user_pictures/badges/14044/18x18.png","badge_starting":"https://static-cdn.jtvnw.net/jtv_user_pictures/badges/14044/72x72.png","badge_3m":null,"badge_6m":null,"badge_12m":null,"badge_24m":null,"set":16609,"emotes":[{"code":"you2DAVAI","image_id":91624},{"code":"you2FR","image_id":94683},{"code":"you2VOK","image_id":103754},{"code":"you2PEC","image_id":89679},{"code":"you2RA","image_id":98829}]}}}
