{"template":{"small":"https://static-cdn.jtvnw.net/emoticons/v1/{image_id}/1.0","medium":"https://static-cdn.jtvnw.net/emoticons/v1/{image_id}/2.0","large":"https://static-cdn.jtvnw.net/emoticons/v1/{image_id}/3.0"},"channels":{"zlfreebird":{"title":"zlfreebird","channel_id":71305314,"link":"http://twitch.tv/zlfreebird","desc":null,"plans":{"$4.99":null,"$9.99":null,"$24.99":null},"id":"zlfreebird","first_seen":null,"badge":null,"badge_starting":null,"badge_3m":null,"badge_6m":null,"badge_12m":null,"badge_24m":null,"badges":null,"bits_badges":null,"cheermote1":null,"cheermote100":null,"cheermote1000":null,"cheermote5000":null,"cheermote10000":null,"set":1520,"emotes":[{"code":"wntrFP","image_id":6848,"set":1520},{"code":"wntrSUP","image_id":6869,"set":1520},{"code":"wntrSwag","image_id":11251,"set":1520},{"code":"wntrMARINE","image_id":30145,"set":1520},{"code":"wntrLOVE","image_id":85301,"set":1520},{"code":"wntrLING","image_id":25989,"set":1520},{"code":"wntrLOT","image_id":25831,"set":1520},{"code":"wntrBOYS","image_id":24999,"set":1520},{"code":"wntrLOOPY","image_id":33658,"set":1520},{"code":"wntrHYPE","image_id":44810,"set":1520},{"code":"wntrGG","image_id":44809,"set":1520},{"code":"wntrWALL","image_id":66443,"set":1520},{"code":"wntrMONEY","image_id":82623,"set":1520},{"code":"wntrDIRTY","image_id":82624,"set":1520},{"code":"wntrHAX","image_id":175629,"set":1520},{"code":"wntrCHEESE","image_id":116409,"set":1520},{"code":"wntrCHAIR","image_id":122212,"set":1520},{"code":"wntrMIS","image_id":164302,"set":1520},{"code":"wntrB","image_id":199147,"set":1520},{"code":"wntrMIND","image_id":199149,"set":1520},{"code":"wntrM","image_id":199176,"set":1520},{"code":"wntrG","image_id":199263,"set":1520},{"code":"wntrCOST","image_id":273277,"set":1520},{"code":"wntrREKT","image_id":273284,"set":1520},{"code":"wntrCHAMP","image_id":273304,"set":1520},{"code":"wntrKEK","image_id":266747,"set":1520},{"code":"wntrLAWN","image_id":273635,"set":1520}]}}}
